{"guide_getting-values.md":"befb1fe4","integrations.md":"22934ad4","guide_property-autocomplete.md":"d8a32ad1","guide_installation.md":"0f36f4ee","loaders_consul.md":"444e30d5","guide_environment-loaders.md":"214a03d6","loaders_env.md":"a0c97042","loaders_etcd.md":"08472675","loaders_file.md":"1b23e92d","loaders_flag.md":"9445279f","loaders_http.md":"3ff5759b","parsers_toml.md":"71bbfdaa","index.md":"fd3b6794","parsers_yaml.md":"741a9b6c","loaders_overview.md":"84907396","loaders_value.md":"a6b8bc46","parsers_overview.md":"73d8c159","loaders_vault.md":"b63d1e29","guide_groups.md":"008840b2","guide_usage.md":"aca87075"}
