{"guide_groups.md":"cf824735","guide_getting-values.md":"1721649b","loaders_env.md":"e77512e8","guide_installation.md":"ace83de3","parsers_overview.md":"11a3fe38","loaders_value.md":"9fd6a2db","guide_environment-loaders.md":"79031e50","index.md":"788565a3","parsers_yaml.md":"5c2a70d6","loaders_http.md":"30730506","loaders_consul.md":"3697c5e4","loaders_overview.md":"1088c3ee","loaders_flag.md":"aa9c406d","integrations.md":"6a5f116f","parsers_toml.md":"069767e9","loaders_vault.md":"45e27f68","guide_property-autocomplete.md":"f99dbd93","loaders_file.md":"7683650f","guide_usage.md":"b314eccd"}
